sort/__init__.py
sort/sort.py
simple_online_realtime_tracking-0.3.dist-info/LICENSE
simple_online_realtime_tracking-0.3.dist-info/METADATA
simple_online_realtime_tracking-0.3.dist-info/WHEEL
simple_online_realtime_tracking-0.3.dist-info/top_level.txt
simple_online_realtime_tracking-0.3.dist-info/RECORD
