Metadata-Version: 2.1
Name: simple-online-realtime-tracking
Version: 0.3
Summary: A simple online and realtime tracking algorithm for 2D multiple object tracking in video sequences
Home-page: https://github.com/timstokman/sort
Author: Alex Bewley
License: UNKNOWN
Platform: UNKNOWN
Classifier: Programming Language :: Python :: 3
Classifier: Operating System :: OS Independent
Classifier: License :: OSI Approved :: GNU General Public License v3 (GPLv3)
Requires-Python: >=3.8
Requires-Dist: filterpy (==1.4.5)
Requires-Dist: lap (==0.4.0)
Requires-Dist: numpy (>=1.18.5)
